dict_tiny/__init__.py
dict_tiny/completer.py
dict_tiny/config.py
dict_tiny/dialog.py
dict_tiny/errors.py
dict_tiny/main.py
dict_tiny/util.py
dict_tiny/version.py
dict_tiny/translators/__init__.py
dict_tiny/translators/deepl_trans.py
dict_tiny/translators/gemini.py
dict_tiny/translators/google_trans.py
dict_tiny/translators/llm.py
dict_tiny/translators/openai.py
dict_tiny/translators/translator.py
dict_tiny/translators/youdao_trans.py
test/__init__.py
test/test_cli.py
test/test_google_trans.py
test/test_utils.py
test/test_youdao_trans.py
test/util.py
dict_tiny-1.3.0.dist-info/LICENSE
dict_tiny-1.3.0.dist-info/METADATA
dict_tiny-1.3.0.dist-info/WHEEL
dict_tiny-1.3.0.dist-info/entry_points.txt
dict_tiny-1.3.0.dist-info/top_level.txt
dict_tiny-1.3.0.dist-info/RECORD
