Metadata-Version: 2.1
Name: dict-tiny
Version: 1.3.0
Summary: A command-line tool that integrates Youdao Dict, Google Translate, Gemini and OpenAI. Just for fun :)
Home-page: https://github.com/louieh/dict-tiny
Author: louie
Author-email: louiehan1015@gmail.com
License: UNKNOWN
Keywords: python youdao dictionary command-line plumbum translator translate google-translation-api gemini openai
Platform: UNKNOWN
Classifier: Environment :: Console
Classifier: Intended Audience :: Developers
Classifier: Operating System :: OS Independent
Classifier: Programming Language :: Python :: 3
Requires-Python: >=3.9
License-File: LICENSE
Requires-Dist: requests
Requires-Dist: lxml
Requires-Dist: plumbum
Requires-Dist: pyperclip
Requires-Dist: prompt-toolkit
Requires-Dist: google-generativeai
Requires-Dist: rich
Requires-Dist: openai
